simpeval/__init__.py
simpeval/cli.py
simpeval/samsa.py
simpeval/aligner/__init__.py
simpeval/aligner/aligner.py
simpeval/aligner/config.py
simpeval/aligner/corenlp_utils.py
simpeval/aligner/utils.py
simpeval/aligner/word_sim.py
simpeval/utils/__init__.py
simpeval/utils/constants.py
simpeval/utils/helpers.py
simpeval/utils/preprocessing.py
simpeval/utils/resources.py
simpeval/utils/ucca_utils.py
simpeval-0.1.0.dist-info/METADATA
simpeval-0.1.0.dist-info/WHEEL
simpeval-0.1.0.dist-info/entry_points.txt
simpeval-0.1.0.dist-info/top_level.txt
simpeval-0.1.0.dist-info/RECORD
