Metadata-Version: 2.1
Name: simpeval
Version: 0.1.0
Summary: Evaluation of text simplification with TUPA and SAMSA
Home-page: https://github.com/jessy3ric/git_memoire/tree/main/annotation_tool
Author: Fernando Alva-Manchego <feralvam@gmail.com>, Louis Martin <louismartincs@gmail.com>, Jessy Nierichlo <jessynchl@gmail.com>,
Classifier: Development Status :: 3 - Alpha
Classifier: Environment :: Console
Classifier: Intended Audience :: Science/Research
Classifier: License :: OSI Approved :: GNU General Public License v3 or later (GPLv3+)
Classifier: Programming Language :: Python :: 3.6
Classifier: Topic :: Text Processing :: Linguistic
Classifier: Topic :: Scientific/Engineering :: Artificial Intelligence
Requires-Dist: click
Requires-Dist: matplotlib
Requires-Dist: nltk (==3.6.5)
Requires-Dist: numpy
Requires-Dist: pandas
Requires-Dist: requests (>=2.21.0)
Requires-Dist: sacrebleu (>=2.0.0)
Requires-Dist: sacremoses
Requires-Dist: tqdm (>=4.32.2)
Requires-Dist: plotly (>=4.0.0)
Requires-Dist: bert-score
Requires-Dist: simalign
Requires-Dist: stanza (>=1.5.0)
Requires-Dist: tupa
